pixelcore/__init__.py
pixelcore/exceptions.py
pixelcore/core/__init__.py
pixelcore/core/color_space.py
pixelcore/core/dtype.py
pixelcore/core/frame.py
pixelcore/core/image.py
pixelcore/core/metadata.py
pixelcore/core/video.py
pixelcore/io/__init__.py
pixelcore/io/image_reader.py
pixelcore/io/image_writer.py
pixelcore/io/video_reader.py
pixelcore/io/video_writer.py
pixelcore/ops/__init__.py
pixelcore/ops/base.py
pixelcore/ops/color/__init__.py
pixelcore/ops/color/balance.py
pixelcore/ops/color/convert.py
pixelcore/ops/color/normalize.py
pixelcore/ops/color/quantize.py
pixelcore/ops/crop/__init__.py
pixelcore/ops/crop/base.py
pixelcore/ops/crop/bbox.py
pixelcore/ops/crop/mask_crop.py
pixelcore/ops/extract/__init__.py
pixelcore/ops/extract/base.py
pixelcore/ops/extract/dominant.py
pixelcore/ops/extract/histogram.py
pixelcore/ops/extract/palette.py
pixelcore/ops/mask/__init__.py
pixelcore/ops/mask/base.py
pixelcore/ops/mask/chroma.py
pixelcore/ops/mask/circle.py
pixelcore/ops/mask/polygon.py
pixelcore/ops/mask/star.py
pixelcore/ops/resize/__init__.py
pixelcore/ops/resize/base.py
pixelcore/ops/resize/bicubic.py
pixelcore/ops/resize/bilinear.py
pixelcore/ops/resize/lanczos.py
pixelcore/ops/resize/nearest.py
pixelcore/pipeline/__init__.py
pixelcore/pipeline/framewise.py
pixelcore/pipeline/pipeline.py
pixelcore/pipeline/presets.py
pixelcore/registry/__init__.py
pixelcore/registry/color.py
pixelcore/registry/extract.py
pixelcore/registry/mask.py
pixelcore/registry/resize.py
pixelcore/utils/__init__.py
pixelcore/utils/geometry.py
pixelcore/utils/math.py
pixelcore/utils/profiling.py
pixelcore/utils/validation.py
pixelcore-0.0.5.dist-info/licenses/LICENSE
pixelcore-0.0.5.dist-info/METADATA
pixelcore-0.0.5.dist-info/WHEEL
pixelcore-0.0.5.dist-info/top_level.txt
pixelcore-0.0.5.dist-info/RECORD
