Metadata-Version: 2.4
Name: pixelcore
Version: 0.0.5
Summary: Core image and video processing primitives
Author: Rishabh Sethi
License-Expression: MIT
Project-URL: Homepage, https://github.com/cruvdev/pixelcore
Project-URL: Repository, https://github.com/cruvdev/pixelcore
Requires-Python: >=3.9
License-File: LICENSE
Provides-Extra: dev
Requires-Dist: black>=24.0; extra == "dev"
Requires-Dist: isort>=5.13; extra == "dev"
Requires-Dist: ruff>=0.4; extra == "dev"
Requires-Dist: pre-commit>=3.6; extra == "dev"
Requires-Dist: build>=1.0; extra == "dev"
Requires-Dist: twine>=5.0; extra == "dev"
Dynamic: license-file
